infrabed/__init__.py
infrabed/client.py
infrabed-0.0.6.dist-info/LICENSE
infrabed-0.0.6.dist-info/METADATA
infrabed-0.0.6.dist-info/WHEEL
infrabed-0.0.6.dist-info/top_level.txt
infrabed-0.0.6.dist-info/RECORD
