Metadata-Version: 2.1
Name: infrabed
Version: 0.0.6
Summary: Python library designed to simplify client-side interaction with deep learning models that perform embedding calculations.
Author: DepDiko
Author-email: <yamen.habib@depdiko.com>
Keywords: python,embedding,deep learning
Classifier: Development Status :: 1 - Planning
Classifier: Intended Audience :: Developers
Classifier: Programming Language :: Python :: 3
Classifier: Operating System :: Unix
Classifier: Operating System :: MacOS :: MacOS X
Classifier: Operating System :: Microsoft :: Windows
License-File: LICENSE
